CHANGES.txt
LICENSE.txt
MANIFEST.in
README.rst
cicero_examples.py
setup.py
test.example.sh
cicero/__init__.py
cicero/cicero_endpoint_constants.py
cicero/cicero_errors.py
cicero/cicero_response_classes.py
cicero/cicero_rest_connection.py
cicero/test/__init__.py
cicero/test/tests.py
docs/cicero_endpoint_constants.html
docs/cicero_errors.html
docs/cicero_response_classes.html
docs/cicero_rest_connection.html
docs/docco.css
docs/index.html
docs/index_styles.css
docs/pycco.css
docs/public/fonts/aller-bold.eot
docs/public/fonts/aller-bold.ttf
docs/public/fonts/aller-bold.woff
docs/public/fonts/aller-light.eot
docs/public/fonts/aller-light.ttf
docs/public/fonts/aller-light.woff
docs/public/fonts/novecento-bold.eot
docs/public/fonts/novecento-bold.ttf
docs/public/fonts/novecento-bold.woff
docs/public/stylesheets/normalize.css
python_cicero.egg-info/PKG-INFO
python_cicero.egg-info/SOURCES.txt
python_cicero.egg-info/dependency_links.txt
python_cicero.egg-info/requires.txt
python_cicero.egg-info/top_level.txt