Metadata-Version: 1.1
Name: python-cicero
Version: 0.1.0
Summary: Python wrapper for Azavea's Cicero API
Home-page: ['http://github.com/azavea/python-cicero']
Author: Andrew Thompson
Author-email: athompson@azavea.com
License: LICENSE.txt
Platform: UNKNOWN
Classifier: Development Status :: 4 - Beta
Classifier: License :: OSI Approved :: Apache Software License
Classifier: Topic :: Scientific/Engineering :: GIS
Classifier: Programming Language :: Python :: 2.7
